torchosr/__init__.py
torchosr/_version.py
torchosr/architectures/__init__.py
torchosr/architectures/architectures.py
torchosr/data/DataWrapper.py
torchosr/data/OutlierDataset.py
torchosr/data/__init__.py
torchosr/data/datasets_config.py
torchosr/data/datasets_config_oneclass.py
torchosr/data/datasets_outlier_config.py
torchosr/data/base_datasets/CIFAR100_base.py
torchosr/data/base_datasets/CIFAR10_base.py
torchosr/data/base_datasets/MNIST_base.py
torchosr/data/base_datasets/Madelon_base.py
torchosr/data/base_datasets/Moonway_base.py
torchosr/data/base_datasets/Omniglot_base.py
torchosr/data/base_datasets/SVHN_base.py
torchosr/data/base_datasets/__init__.py
torchosr/models/GSL.py
torchosr/models/NoiseSoftmax.py
torchosr/models/Openmax.py
torchosr/models/OverlaySoftmax.py
torchosr/models/TSoftmax.py
torchosr/models/__init__.py
torchosr/models/base.py
torchosr/tests/__init__.py
torchosr/tests/test_common.py
torchosr/tests/test_data.py
torchosr/utils/__init__.py
torchosr/utils/base.py
torchosr-0.1.6.dist-info/LICENSE
torchosr-0.1.6.dist-info/METADATA
torchosr-0.1.6.dist-info/WHEEL
torchosr-0.1.6.dist-info/top_level.txt
torchosr-0.1.6.dist-info/RECORD
