Metadata-Version: 2.2
Name: torchosr
Version: 0.1.6
Summary: The torchosr module is a set of tools necessary for processing open set recognition problems with pytorch.
Home-page: https://github.com/w4k2/torchosr
Download-URL: https://github.com/w4k2/torchosr
Maintainer: J. Komorniczak
Maintainer-email: joanna.komorniczak@pwr.edu.pl
License: GPL-3.0
Classifier: Development Status :: 4 - Beta
Classifier: Intended Audience :: Science/Research
Classifier: License :: OSI Approved :: GNU General Public License v3 (GPLv3)
Classifier: Programming Language :: Python
Classifier: Programming Language :: Python :: 3.7
Classifier: Topic :: Scientific/Engineering
Classifier: Topic :: Scientific/Engineering :: Artificial Intelligence
Classifier: Topic :: Software Development :: Libraries
Classifier: Topic :: Software Development :: Libraries :: Python Modules
License-File: LICENSE
Requires-Dist: numpy
Requires-Dist: scipy
Requires-Dist: torch
Requires-Dist: torchvision
Requires-Dist: torchmetrics
Requires-Dist: scikit-learn
Dynamic: classifier
Dynamic: description
Dynamic: description-content-type
Dynamic: download-url
Dynamic: home-page
Dynamic: license
Dynamic: maintainer
Dynamic: maintainer-email
Dynamic: requires-dist
Dynamic: summary
